{
  "slug": "stone-aegis",
  "name": "Stone Aegis",
  "desc": "A rocky coating covers your body, protecting you. Until the start of your next turn, you gain 5 temporary hit points and a +2 bonus to Armor Class, including against the triggering attack.\n  At the start of each of your subsequent turns, you can use a bonus action to extend the duration of the AC bonus until the start of your following turn, for up to 1 minute.",
  "higher_level": "",
  "level": "1st-level",
  "level_int": 1,
  "school": "transmutation",
  "components": "V, S",
  "requires_verbal_components": true,
  "requires_somatic_components": true,
  "requires_material_components": false,
  "material": "",
  "can_be_cast_as_ritual": false,
  "ritual": "no",
  "duration": "Up to 1 minute",
  "concentration": "no",
  "requires_concentration": false,
  "casting_time": "1 reaction, which you take when you are hit by an attack",
  "range": "Self",
  "target_range_sort": 0,
  "spell_level": 1,
  "dnd_class": "Cleric, Druid, Warlock",
  "spell_lists": []
}