{
  "slug": "mule_bf",
  "name": "Mule",
  "size": "medium",
  "type": "Beast",
  "subtype": "",
  "group": "Animals",
  "alignment": "",
  "armor_class": 10,
  "armor_desc": null,
  "hit_points": 10,
  "hit_dice": "",
  "speed": {
    "walk": 40
  },
  "strength": 14,
  "dexterity": 10,
  "constitution": 12,
  "intelligence": 2,
  "wisdom": 10,
  "charisma": 4,
  "skills": {},
  "damage_vulnerabilities": "",
  "damage_resistances": "exhaustion,prone",
  "damage_immunities": "",
  "condition_immunities": "",
  "senses": "-",
  "languages": "-",
  "cr": 0.125,
  "challenge_rating": "1/8",
  "actions": [
    {
      "name": "Hooves",
      "desc": "_Melee Weapon Attack:_ +4 to hit, reach 5 ft., one target. _Hit:_ 4 (1d4+2) bludgeoning damage."
    }
  ],
  "special_abilities": [
    {
      "name": "Beast of Burden",
      "desc": "The mule is considered to be a Large animal for the purpose of determining its carrying capacity."
    }
  ],
  "legendary_actions": []
}